setup.py
lightnn/__init__.py
lightnn/ops.py
lightnn/utils.py
lightnn.egg-info/PKG-INFO
lightnn.egg-info/SOURCES.txt
lightnn.egg-info/dependency_links.txt
lightnn.egg-info/not-zip-safe
lightnn.egg-info/top_level.txt
lightnn/base/__init__.py
lightnn/base/activations.py
lightnn/base/initializers.py
lightnn/base/losses.py
lightnn/base/optimizers.py
lightnn/examples/NeuralNetwork.py
lightnn/examples/__init__.py
lightnn/examples/lm.py
lightnn/examples/mnist.py
lightnn/layers/__init__.py
lightnn/layers/convolutional.py
lightnn/layers/core.py
lightnn/layers/layer.py
lightnn/layers/pooling.py
lightnn/layers/recurrent.py
lightnn/models/__init__.py
lightnn/models/models.py
lightnn/test/__init__.py
lightnn/test/cnn_gradient_check.py
lightnn/test/nn_gradient_check.py
lightnn/test/rnn_gradient_check.py
lightnn/test/test_activators.py