Metadata-Version: 1.1
Name: lightnn
Version: 0.0.7
Summary: This package can download funds data from https://github.com/l11x0m7/lightnn. For details, please visit https://skyhigh233.com.
Home-page: https://github.com/l11x0m7/lightnn
Author: Xuming Lin
Author-email: l11x0m7@gmail.com
License: Apache License, Version 2.0
Platform: UNKNOWN
Classifier: Development Status :: 3 - Alpha
Classifier: Intended Audience :: Developers
Classifier: Operating System :: OS Independent
Classifier: Programming Language :: Python
